[
  {
    "name": "canopy Lights",
    "imagePath": "/src/images/canopyLight.png",
    "altText": "canopy"
  },
  {
    "name": "flood lights",
    "imagePath": "/src/images/floodLight.png",
    "altText": "flood"
  },
  {
    "name": "parking lot Lights",
    "imagePath": "/src/images/parkingLight.png",
    "altText": "parking lot"
  },
  {
    "name": "barn Lights",
    "imagePath": "/src/images/barnLight.png",
    "altText": "barn light"
  },
  {
    "name": "sports lighting",
    "imagePath": "/src/images/sportsLight.png",
    "altText": "sports light"
  },
  {
    "name": "wallpacks",
    "imagePath": "/src/images/wallpack.png",
    "altText": "wallpacks"
  }
]
